MANIFEST.in
README.md
VERSION
setup.py
pyNakadi/__init__.py
pyNakadi/client.py
pyNakadi.egg-info/PKG-INFO
pyNakadi.egg-info/SOURCES.txt
pyNakadi.egg-info/dependency_links.txt
pyNakadi.egg-info/not-zip-safe
pyNakadi.egg-info/requires.txt
pyNakadi.egg-info/top_level.txt